Workbook

Sheet Petunjuk
A1: Judul | B1: Draft penulisan ulang 23 Template Sistem wa-inbox mengikuti panduan "Arsitektur & Hierarki Struktur Pesan"
A2: Status | B2: DITERAPKAN — ke-23 draft aktif di produksi sejak 22 Sep 2026 (script apply-template-drafts, 23 baris audit log). Kolom "Template lama" = isi sebelum diterapkan; cadangan lengkapnya: docs/system-templates/cadangan-template-sebelum-draft-2026-09-22.json.
A3: Sumber template lama | B3: Diambil langsung dari database produksi wa-inbox (tabel SystemTemplate) pada 22 September 2026. Sejak seed, satu-satunya perubahan adalah penggantian tautan ke short link jvto.me (22 Sep 2026, tercatat di audit log).
A4: Isi file | B4: 1) Panduan per Poin — panduan dipecah jadi 17 poin + cara diterapkan + aturan pemeriksanya. 2) Template Lama vs Baru — teks mentah & preview (dengan nilai contoh) lama dan baru, plus alasan perubahan. 3) Cek Kepatuhan — matriks 23 template × 19 aturan (14 dari panduan, 5 integritas), dihitung dengan rumus. 4) Detail Cek — catatan pemeriksa per template per aturan.
A5: Cara membaca | B5: Kolom "Template" berisi teks mentah persis seperti yang akan disimpan (dengan {variabel}). Kolom "Preview" adalah hasil render renderer produksi wa-inbox memakai nilai contoh (data palsu, mis. John Doe). Format WhatsApp: *tebal*, _miring_, `monospace`, ~coret~.
A6: Warna | B6: Abu-abu = template lama · Hijau = draft baru · Di Cek Kepatuhan: hijau OK, abu-abu N/A (aturan tidak berlaku), merah GAGAL.
A7: Bagaimana diperiksa | B7: Setiap poin panduan yang bisa diukur dijadikan aturan mesin. Semua 23 draft lulus 19 aturan. Setiap aturan juga sudah diuji bisa GAGAL pada contoh yang sengaja melanggar, jadi "lulus" bukan karena aturannya longgar.
A8: Yang tidak diubah | B8: Bahasa tiap pesan (pelanggan tetap Inggris; internal tetap seperti aslinya, kecuali label hotel diseragamkan ke Bahasa Indonesia), fakta & tautan, dan daftar variabel — draft bisa disimpan tanpa mengubah kode javavolcano-touroperator / new-backoffice. Variabel booking_short (kode tautan jvto.me/b/) sudah dideklarasikan di produksi pada 8 template yang memakainya.
A9: Teks yang benar-benar baru | B9: Beberapa kalimat CTA di pesan internal adalah teks baru (mis. "Mohon siapkan unit sesuai jadwal di atas", "Check the full answers in Typeform", "Mohon sesuaikan produksi kaos…"). Ditandai di kolom Perubahan utama. Periksa apakah instruksinya sesuai praktik lapangan.
A10: Risiko format | B10: `monospace` satu-backtick baru dirender oleh aplikasi WhatsApp versi 2024 ke atas; di versi lama backtick tampil apa adanya. Kalau ini jadi masalah, ganti dengan ```tiga backtick``` (didukung lebih lama).
A11: Batas panduan | B11: Panduan ini adalah kumpulan praktik baik, bukan hasil pengukuran di pelanggan JVTO. Cara terbaik membuktikan manfaatnya: terapkan pada 1–2 template (mis. booking_pending_payment, payment_reminder_balance) lalu bandingkan tingkat pembayaran/balasan sebelum dan sesudah.
A12: Cara menerapkan | B12: Pilih template yang disetujui → buka wa-inbox → Template → Template Sistem → pilih key → tempel isi kolom "Draft template baru (teks mentah)" → Simpan. Langsung berlaku untuk kiriman berikutnya.

Sheet Template Lama vs Baru
A1: No | B1: Key | C1: Nama | D1: Penerima | E1: Kapan dikirim | F1: Gambar | G1: Variabel (* = wajib) | H1: Template lama (teks mentah) | I1: Draft template baru (teks mentah) | J1: Preview lama (nilai contoh) | K1: Preview baru (nilai contoh) | L1: Perubahan utama & alasan | M1: Hasil cek (rumus)
A2: 1 | B2: booking_confirmed_backoffice_jvto | C2: Booking dibuat dari backoffice — JVTO | D2: Pelanggan | E2: Dikirim ke pelanggan (gambar + caption) saat admin membuat booking non-Klook di new-backoffice dengan opsi kirim WA aktif. | F2: Ya | G2: customer_name* booking_slug* booking_short* | H2: ✅ *Booking Confirmed – Java Volcano Tour Operator (JVTO)* Thank you, {customer_name}, for completing your *booking*. We’re pleased to confirm that your *tour booking is now secured*. 📩 Your *payment receipt, remaining balance, payment method*, and *tour itinerary* have all been sent to your registered email address. Please kindly check your inbox (and spam folder just in case), or you can access it directly via the link below 🔗 https://jvto.me/b/{booking_short} If you have any questions or special requests, feel free to contact us via WhatsApp or email. 🙏 We truly appreciate your trust. We look forward to welcoming you on an unforgettable journey! *JVTO Team* | I2: ✅ *[BOOKING CONFIRMED] Your JVTO tour is secured* Hi _{customer_name}_, thank you for completing your booking with Java Volcano Tour Operator. 📩 *Check your email:* your payment receipt, remaining balance, payment method and tour itinerary have been sent to your registered address. _Not in your inbox? Please check the spam folder too._ 💬 *Questions or special requests?* Reply to this chat or email hello@javavolcano-touroperator.com 👉 *Open your booking details here:* https://jvto.me/b/{booking_short} _🙏 Thank you for your trust. We look forward to welcoming you on an unforgettable journey! — JVTO Team_ | J2: ✅ *Booking Confirmed – Java Volcano Tour Operator (JVTO)* Thank you, John Doe, for completing your *booking*. We’re pleased to confirm that your *tour booking is now secured*. 📩 Your *payment receipt, remaining balance, payment method*, and *tour itinerary* have all been sent to your registered email address. Please kindly check your inbox (and spam folder just in case), or you can access it directly via the link below 🔗 https://jvto.me/b/Ab3dE5fG7h If you have any questions or special requests, feel free to contact us via WhatsApp or email. 🙏 We truly appreciate your trust. We look forward to welcoming you on an unforgettable journey! *JVTO Team* | K2: ✅ *[BOOKING CONFIRMED] Your JVTO tour is secured* Hi _John Doe_, thank you for completing your booking with Java Volcano Tour Operator. 📩 *Check your email:* your payment receipt, remaining balance, payment method and tour itinerary have been sent to your registered address. _Not in your inbox? Please check the spam folder too._ 💬 *Questions or special requests?* Reply to this chat or email hello@javavolcano-touroperator.com 👉 *Open your booking details here:* https://jvto.me/b/Ab3dE5fG7h _🙏 Thank you for your trust. We look forward to welcoming you on an unforgettable journey! — JVTO Team_ | L2: Hook berlabel [BOOKING CONFIRMED] + emoji di baris 1; paragraf panjang (4 baris) dipecah jadi blok ≤3 baris; kata kunci tebal di awal baris; tautan dipindah ke bawah sebagai CTA tebal; penutup & tanda tangan jadi catatan kaki miring. Email kontak diambil dari template lain (fakta yang sudah ada). Tautan portal booking: jvto.me/b/{booking_short} — sudah aktif di produksi sejak 22 Sep 2026 (template lama ikut diganti). | M2: =IF('Cek Kepatuhan'!X2=0,"Lulus: "&'Cek Kepatuhan'!V2&" OK, "&'Cek Kepatuhan'!W2&" N/A","GAGAL "&'Cek Kepatuhan'!X2&" aturan")
A3: 2 | B3: booking_confirmed_backoffice_klook | C3: Booking dibuat dari backoffice — Klook | D3: Pelanggan | E3: Dikirim ke pelanggan (gambar + caption) saat admin membuat booking Klook (booking_category_id = 3) di new-backoffice dengan opsi kirim WA aktif. | F3: Ya | G3: customer_name* booking_slug* booking_short* | H3: ✅ *Booking Confirmed – Java Volcano Tour Operator (JVTO)* Thank you, {customer_name}, for completing your *booking*. We’re pleased to confirm that your *tour booking is now secured*. 📩 If you have any questions or special requests, feel free to contact us via WhatsApp or email. For detailed trip information, you can check directly at the following link: https://jvto.me/b/{booking_short} 🙏 We truly appreciate your trust. We look forward to welcoming you on an unforgettable journey! *JVTO Team* | I3: ✅ *[BOOKING CONFIRMED] Your JVTO tour is secured* Hi _{customer_name}_, thank you for completing your booking with Java Volcano Tour Operator. 💬 *Questions or special requests?* Reply to this chat or email hello@javavolcano-touroperator.com 👉 *See your full trip details here:* https://jvto.me/b/{booking_short} _🙏 Thank you for your trust. We look forward to welcoming you on an unforgettable journey! — JVTO Team_ | J3: ✅ *Booking Confirmed – Java Volcano Tour Operator (JVTO)* Thank you, John Doe, for completing your *booking*. We’re pleased to confirm that your *tour booking is now secured*. 📩 If you have any questions or special requests, feel free to contact us via WhatsApp or email. For detailed trip information, you can check directly at the following link: https://jvto.me/b/Ab3dE5fG7h 🙏 We truly appreciate your trust. We look forward to welcoming you on an unforgettable journey! *JVTO Team* | K3: ✅ *[BOOKING CONFIRMED] Your JVTO tour is secured* Hi _John Doe_, thank you for completing your booking with Java Volcano Tour Operator. 💬 *Questions or special requests?* Reply to this chat or email hello@javavolcano-touroperator.com 👉 *See your full trip details here:* https://jvto.me/b/Ab3dE5fG7h _🙏 Thank you for your trust. We look forward to welcoming you on an unforgettable journey! — JVTO Team_ | L3: Sama dengan versi JVTO tanpa blok email (booking Klook memang tidak menerima email dari JVTO). Tautan detail trip, yang tadinya di tengah paragraf, jadi CTA tebal di bawah. Tautan portal booking: jvto.me/b/{booking_short} — sudah aktif di produksi sejak 22 Sep 2026 (template lama ikut diganti). | M3: =IF('Cek Kepatuhan'!X3=0,"Lulus: "&'Cek Kepatuhan'!V3&" OK, "&'Cek Kepatuhan'!W3&" N/A","GAGAL "&'Cek Kepatuhan'!X3&" aturan")
A4: 3 | B4: booking_confirmed_klook_email | C4: Booking Klook dari email terkonfirmasi | D4: Pelanggan | E4: Dikirim ke pelanggan (gambar + caption) saat booking Klook dibuat otomatis dari email Klook yang diekstrak. | F4: Ya | G4: customer_name* package_name* total_pax* booking_slug* booking_short* | H4: *Booking Confirmed!* ✅🎉 Dear {customer_name}, We're thrilled to confirm your booking! 🎉 Below are the details of your upcoming trip: *Your Booking Details* - *Tour Package*: {package_name} - *Number of Pax*: {total_pax} Pax *Access Your Personalized Trip Dashboard* 📊 https://jvto.me/b/{booking_short} *What's Next?* - Your booking is confirmed, you can check your trip detail through Trip Dasbboard. *Need Help?* Contact us: - WhatsApp: +62 822-4478-8833 - Email: hello@javavolcano-touroperator.com Let's Get Ready to Explore! 🎉 We're looking forward to helping you create unforgettable memories! Best regards, JVTO Team 🚐 | I4: ✅ *[BOOKING CONFIRMED] Your trip is booked* 🎉 Dear _{customer_name}_, we're thrilled to confirm your booking. 🗺️ *Tour Package:* {package_name} 👥 *Guests:* {total_pax} pax 💬 *Need help?* Reply to this chat 📞 *WhatsApp:* +62 822-4478-8833 📧 *Email:* hello@javavolcano-touroperator.com 👉 *Open your Trip Dashboard for all trip details:* https://jvto.me/b/{booking_short} _Let's get ready to explore — we look forward to creating unforgettable memories with you! — JVTO Team 🚐_ | J4: *Booking Confirmed!* ✅🎉 Dear John Doe, We're thrilled to confirm your booking! 🎉 Below are the details of your upcoming trip: *Your Booking Details* - *Tour Package*: Bromo Ijen Tour 3 Days 2 Nights - *Number of Pax*: 2 Pax *Access Your Personalized Trip Dashboard* 📊 https://jvto.me/b/Ab3dE5fG7h *What's Next?* - Your booking is confirmed, you can check your trip detail through Trip Dasbboard. *Need Help?* Contact us: - WhatsApp: +62 822-4478-8833 - Email: hello@javavolcano-touroperator.com Let's Get Ready to Explore! 🎉 We're looking forward to helping you create unforgettable memories! Best regards, JVTO Team 🚐 | K4: ✅ *[BOOKING CONFIRMED] Your trip is booked* 🎉 Dear _John Doe_, we're thrilled to confirm your booking. 🗺️ *Tour Package:* Bromo Ijen Tour 3 Days 2 Nights 👥 *Guests:* 2 pax 💬 *Need help?* Reply to this chat 📞 *WhatsApp:* +62 822-4478-8833 📧 *Email:* hello@javavolcano-touroperator.com 👉 *Open your Trip Dashboard for all trip details:* https://jvto.me/b/Ab3dE5fG7h _Let's get ready to explore — we look forward to creating unforgettable memories with you! — JVTO Team 🚐_ | L4: Hook berlabel; blok 'What's Next' yang hanya mengulang 'booking confirmed' digabung ke CTA; typo 'Trip Dasbboard' hilang; data paket/pax diberi jangkar emoji di kiri; blok kontak 3 baris; penutup miring. Tautan portal booking: jvto.me/b/{booking_short} — sudah aktif di produksi sejak 22 Sep 2026 (template lama ikut diganti). | M4: =IF('Cek Kepatuhan'!X4=0,"Lulus: "&'Cek Kepatuhan'!V4&" OK, "&'Cek Kepatuhan'!W4&" N/A","GAGAL "&'Cek Kepatuhan'!X4&" aturan")
A5: 4 | B5: booking_pending_payment | C5: Booking dibuat — menunggu pembayaran | D5: Pelanggan | E5: Dikirim ke pelanggan saat checkout website membuat booking yang belum dibayar, berisi ringkasan booking dan tautan pembayaran. | F5: — | G5: customer_name* booking_id* tour_package* travel_dates* pax* amount_due* payment_type* payment_method* payment_link* payment_deadline* | H5: *[JVTO] Booking Pending — Payment Required* ⏳ Hi _{customer_name}_, thank you for booking with *JVTO*. Your booking has been created and is currently *pending payment*. *Booking Summary* - *Booking ID:* {booking_id} - *Tour Package:* {tour_package} - *Travel Dates:* {travel_dates} - *Guests (Pax):* {pax} - *Status:* Pending (Awaiting Payment) *Amount Due:* IDR {amount_due} *Payment Type:* {payment_type} *Payment Method:* {payment_method} Please complete your payment using this official link: 👉 {payment_link} *Payment deadline:* {payment_deadline} *Notes* - Your booking will be confirmed automatically once payment is successful. - *Security:* JVTO will never ask for your OTP/PIN. Please pay only via the link above. *Need help?* Reply to this chat or contact: - WhatsApp: +62 822-4478-8833 - Email: hello@javavolcano-touroperator.com — JVTO Team | I5: ⏳ *[PAYMENT REQUIRED] Your JVTO booking is on hold* Hi _{customer_name}_, your booking is created and *pending payment*. It will be confirmed automatically once your payment succeeds. 🧾 *Booking ID:* `{booking_id}` 🗺️ *Tour Package:* {tour_package} 📅 *Travel Dates:* {travel_dates} 👥 *Guests:* {pax} pax 💳 *Payment:* {payment_type} via {payment_method} 💰 *Amount Due:* `IDR {amount_due}` ⏰ *Pay before:* {payment_deadline} 💬 *Need help?* Reply to this chat, WhatsApp +62 822-4478-8833 or email hello@javavolcano-touroperator.com 👉 *Complete your payment now:* {payment_link} _🔒 JVTO will never ask for your OTP/PIN. Please pay only via the link above. — JVTO Team_ | J5: *[JVTO] Booking Pending — Payment Required* ⏳ Hi _John Doe_, thank you for booking with *JVTO*. Your booking has been created and is currently *pending payment*. *Booking Summary* - *Booking ID:* JVTO-2026-0001 - *Tour Package:* Bromo Ijen Tour 3 Days 2 Nights - *Travel Dates:* 12 October 2026 - 14 October 2026 - *Guests (Pax):* 2 - *Status:* Pending (Awaiting Payment) *Amount Due:* IDR 1.500.000 *Payment Type:* Deposit *Payment Method:* Credit/Debit Card (XENDIT) Please complete your payment using this official link: 👉 https://checkout.xendit.co/web/example-invoice-0001 *Payment deadline:* 05 October 2026 23:59 WIB *Notes* - Your booking will be confirmed automatically once payment is successful. - *Security:* JVTO will never ask for your OTP/PIN. Please pay only via the link above. *Need help?* Reply to this chat or contact: - WhatsApp: +62 822-4478-8833 - Email: hello@javavolcano-touroperator.com — JVTO Team | K5: ⏳ *[PAYMENT REQUIRED] Your JVTO booking is on hold* Hi _John Doe_, your booking is created and *pending payment*. It will be confirmed automatically once your payment succeeds. 🧾 *Booking ID:* `JVTO-2026-0001` 🗺️ *Tour Package:* Bromo Ijen Tour 3 Days 2 Nights 📅 *Travel Dates:* 12 October 2026 - 14 October 2026 👥 *Guests:* 2 pax 💳 *Payment:* Deposit via Credit/Debit Card (XENDIT) 💰 *Amount Due:* `IDR 1.500.000` ⏰ *Pay before:* 05 October 2026 23:59 WIB 💬 *Need help?* Reply to this chat, WhatsApp +62 822-4478-8833 or email hello@javavolcano-touroperator.com 👉 *Complete your payment now:* https://checkout.xendit.co/web/example-invoice-0001 _🔒 JVTO will never ask for your OTP/PIN. Please pay only via the link above. — JVTO Team_ | L5: Urgensi (belum dibayar) naik ke hook; ringkasan 5 baris dipecah jadi 3 blok ≤3 baris; nominal & ID booking diisolasi dengan monospace; tenggat ditaruh tepat di bawah nominal; tautan bayar pindah ke paling bawah sebagai CTA tebal; peringatan OTP jadi catatan kaki miring. Baris 'Status: Pending' sudah terwakili di hook & kalimat pembuka. | M5: =IF('Cek Kepatuhan'!X5=0,"Lulus: "&'Cek Kepatuhan'!V5&" OK, "&'Cek Kepatuhan'!W5&" N/A","GAGAL "&'Cek Kepatuhan'!X5&" aturan")
A6: 5 | B6: payment_method_confirmed_card | C6: Metode pelunasan dipilih — Kartu (Xendit) | D6: Pelanggan | E6: Dikirim ke pelanggan saat ia memilih kartu kredit/debit (Xendit) untuk pelunasan; berisi tautan invoice Xendit yang baru dibuat (setPaymentMethod, type=cc). | F6: — | G6: customer_name* remaining_balance* payment_link* | H6: Dear {customer_name}, Thank you for confirming your payment method. You have selected the following payment option for the remaining balance of your tour: 🔹 *Payment Method:* Credit/Debit Card (XENDIT) 💰 *Remaining Balance:* IDR {remaining_balance} 🔗 *Payment Link:* {payment_link} If you have any questions or need assistance, we are happy to help. Warm regards, JVTO Team 🌋 Explore Java’s Volcanoes with Us | I6: ✅ *[PAYMENT METHOD CONFIRMED] Credit/Debit Card* Dear _{customer_name}_, thank you for confirming how you will pay the remaining balance of your tour. 💳 *Method:* Credit/Debit Card (XENDIT) 💰 *Remaining Balance:* `IDR {remaining_balance}` 💬 *Questions?* Reply to this chat — we are happy to help. 👉 *Pay your balance securely here:* {payment_link} _Warm regards, JVTO Team — 🌋 Explore Java's Volcanoes with Us_ | J6: Dear John Doe, Thank you for confirming your payment method. You have selected the following payment option for the remaining balance of your tour: 🔹 *Payment Method:* Credit/Debit Card (XENDIT) 💰 *Remaining Balance:* IDR 3.250.000 🔗 *Payment Link:* https://checkout.xendit.co/web/example-invoice-0002 If you have any questions or need assistance, we are happy to help. Warm regards, JVTO Team 🌋 Explore Java’s Volcanoes with Us | K6: ✅ *[PAYMENT METHOD CONFIRMED] Credit/Debit Card* Dear _John Doe_, thank you for confirming how you will pay the remaining balance of your tour. 💳 *Method:* Credit/Debit Card (XENDIT) 💰 *Remaining Balance:* `IDR 3.250.000` 💬 *Questions?* Reply to this chat — we are happy to help. 👉 *Pay your balance securely here:* https://checkout.xendit.co/web/example-invoice-0002 _Warm regards, JVTO Team — 🌋 Explore Java's Volcanoes with Us_ | L6: Hook berlabel memuat metode yang dipilih; nominal monospace; tautan invoice pindah ke bawah sebagai CTA tebal; salam & slogan jadi catatan kaki miring. Spasi berlebih di akhir baris saldo hilang. | M6: =IF('Cek Kepatuhan'!X6=0,"Lulus: "&'Cek Kepatuhan'!V6&" OK, "&'Cek Kepatuhan'!W6&" N/A","GAGAL "&'Cek Kepatuhan'!X6&" aturan")
A7: 6 | B7: payment_method_confirmed_cash | C7: Metode pelunasan dipilih — Cash | D7: Pelanggan | E7: Dikirim ke pelanggan saat ia memilih Cash sebagai metode pelunasan sisa tagihan (setPaymentMethod, type=cash). | F7: — | G7: customer_name* remaining_balance* | H7: Dear {customer_name}, Thank you for confirming your payment method. You have selected the following payment option for the remaining balance of your tour: 🔹 *Payment Method:* Cash 💰 *Remaining Balance:* IDR {remaining_balance} 🔗 *Payment information:* https://jvto.me/booking If you have any questions or need assistance, we are happy to help. Warm regards, JVTO Team 🌋 Explore Java’s Volcanoes with Us | I7: ✅ *[PAYMENT METHOD CONFIRMED] Cash* Dear _{customer_name}_, thank you for confirming how you will pay the remaining balance of your tour. 💵 *Method:* Cash 💰 *Remaining Balance:* `IDR {remaining_balance}` 💬 *Questions?* Reply to this chat — we are happy to help. 👉 *See the payment information here:* https://jvto.me/booking _Warm regards, JVTO Team — 🌋 Explore Java's Volcanoes with Us_ | J7: Dear John Doe, Thank you for confirming your payment method. You have selected the following payment option for the remaining balance of your tour: 🔹 *Payment Method:* Cash 💰 *Remaining Balance:* IDR 3.250.000 🔗 *Payment information:* https://jvto.me/booking If you have any questions or need assistance, we are happy to help. Warm regards, JVTO Team 🌋 Explore Java’s Volcanoes with Us | K7: ✅ *[PAYMENT METHOD CONFIRMED] Cash* Dear _John Doe_, thank you for confirming how you will pay the remaining balance of your tour. 💵 *Method:* Cash 💰 *Remaining Balance:* `IDR 3.250.000` 💬 *Questions?* Reply to this chat — we are happy to help. 👉 *See the payment information here:* https://jvto.me/booking _Warm regards, JVTO Team — 🌋 Explore Java's Volcanoes with Us_ | L7: Struktur sama dengan versi kartu; CTA menunjuk halaman informasi pembayaran yang sama seperti sebelumnya. Tautan /payment-information (410) diganti ke https://jvto.me/booking → halaman Booking Information; aktif di produksi 22 Sep 2026 (template lama ikut diganti). URL lama juga di-301 ke halaman yang sama. | M7: =IF('Cek Kepatuhan'!X7=0,"Lulus: "&'Cek Kepatuhan'!V7&" OK, "&'Cek Kepatuhan'!W7&" N/A","GAGAL "&'Cek Kepatuhan'!X7&" aturan")
A8: 7 | B8: payment_method_confirmed_wise | C8: Metode pelunasan dipilih — Wise | D8: Pelanggan | E8: Dikirim ke pelanggan saat ia memilih Wise Transfer sebagai metode pelunasan sisa tagihan (setPaymentMethod, type=wise). | F8: — | G8: customer_name* remaining_balance* | H8: Dear {customer_name}, Thank you for confirming your payment method. You have selected the following payment option for the remaining balance of your tour: 🔹 *Payment Method:* Wise Transfer 💰 *Remaining Balance:* IDR {remaining_balance} 🔗 *Payment information:* https://jvto.me/booking If you have any questions or need assistance, we are happy to help. Warm regards, JVTO Team 🌋 Explore Java’s Volcanoes with Us | I8: ✅ *[PAYMENT METHOD CONFIRMED] Wise Transfer* Dear _{customer_name}_, thank you for confirming how you will pay the remaining balance of your tour. 🏦 *Method:* Wise Transfer 💰 *Remaining Balance:* `IDR {remaining_balance}` 💬 *Questions?* Reply to this chat — we are happy to help. 👉 *See the payment information here:* https://jvto.me/booking _Warm regards, JVTO Team — 🌋 Explore Java's Volcanoes with Us_ | J8: Dear John Doe, Thank you for confirming your payment method. You have selected the following payment option for the remaining balance of your tour: 🔹 *Payment Method:* Wise Transfer 💰 *Remaining Balance:* IDR 3.250.000 🔗 *Payment information:* https://jvto.me/booking If you have any questions or need assistance, we are happy to help. Warm regards, JVTO Team 🌋 Explore Java’s Volcanoes with Us | K8: ✅ *[PAYMENT METHOD CONFIRMED] Wise Transfer* Dear _John Doe_, thank you for confirming how you will pay the remaining balance of your tour. 🏦 *Method:* Wise Transfer 💰 *Remaining Balance:* `IDR 3.250.000` 💬 *Questions?* Reply to this chat — we are happy to help. 👉 *See the payment information here:* https://jvto.me/booking _Warm regards, JVTO Team — 🌋 Explore Java's Volcanoes with Us_ | L8: Struktur sama dengan versi kartu; CTA menunjuk halaman informasi pembayaran yang sama seperti sebelumnya. Tautan /payment-information (410) diganti ke https://jvto.me/booking → halaman Booking Information; aktif di produksi 22 Sep 2026 (template lama ikut diganti). URL lama juga di-301 ke halaman yang sama. | M8: =IF('Cek Kepatuhan'!X8=0,"Lulus: "&'Cek Kepatuhan'!V8&" OK, "&'Cek Kepatuhan'!W8&" N/A","GAGAL "&'Cek Kepatuhan'!X8&" aturan")
A9: 8 | B9: payment_received_balance | C9: Pelunasan diterima | D9: Pelanggan | E9: Dikirim ke pelanggan (gambar + caption) saat webhook Xendit menerima pembayaran "#Outstanding Payment" (pelunasan sisa tagihan). | F9: Ya | G9: customer_name* booking_code* package_name* travel_date_start* travel_date_end* pickup* total_pax* payment_amount* payment_type* payment_status* booking_slug* booking_short* | H9: *[JVTO] Booking Confirmed — Payment Received* ✅🎉 Hi _{customer_name}_, thank you for your payment. Your booking is now *confirmed*. *Booking Details* - *Booking ID:* {booking_code} - *Tour Package:* {package_name} - *Travel Dates:* {travel_date_start} - {travel_date_end} - *Pickup Location:* {pickup} - *Guests (Pax):* {total_pax} - *Status:* Confirmed *Payment Summary* - *Payment Received:* IDR {payment_amount} - *Payment Type:* {payment_type} - *Payment Status:* {payment_status} *Trip Dashboard* 📊 View your itinerary, pickup details, accommodation, and trip updates here: 👉 https://jvto.me/b/{booking_short} *Notes* - Any confirmed updates will appear in the Trip Dashboard. - If a remaining balance applies, we will share the payment link and deadline in a separate message. - Please review the Trip Dashboard and tell us if any details need correction. *Need help?* Reply to this chat or contact: - WhatsApp: +62 822-4478-8833 - Email: hello@javavolcano-touroperator.com *Security:* JVTO will never ask for your OTP/PIN. Please use only official links shared in this chat. — JVTO Team | I9: ✅ *[PAYMENT RECEIVED] Your booking is confirmed* 🎉 Hi _{customer_name}_, thank you for your payment. 🧾 *Booking ID:* `{booking_code}` 🗺️ *Tour Package:* {package_name} 📅 *Travel Dates:* {travel_date_start} – {travel_date_end} 📍 *Pickup:* {pickup} 👥 *Guests:* {total_pax} pax ✅ *Status:* Confirmed 💰 *Payment Received:* `IDR {payment_amount}` 💳 *Payment Type:* {payment_type} 📊 *Payment Status:* {payment_status} 📌 *Please note* - Confirmed updates appear in your Trip Dashboard. - If a remaining balance applies, we will send the payment link and deadline separately. 💬 *Need help?* Reply to this chat, WhatsApp +62 822-4478-8833 or email hello@javavolcano-touroperator.com 👉 *Review your itinerary, pickup and accommodation in the Trip Dashboard — tell us if anything needs correcting:* https://jvto.me/b/{booking_short} _🔒 JVTO will never ask for your OTP/PIN. Please use only official links shared in this chat. — JVTO Team_ | J9: *[JVTO] Booking Confirmed — Payment Received* ✅🎉 Hi _John Doe_, thank you for your payment. Your booking is now *confirmed*. *Booking Details* - *Booking ID:* JVTO-2026-0001 - *Tour Package:* Bromo Ijen Tour 3 Days 2 Nights - *Travel Dates:* 12 October 2026 - 14 October 2026 - *Pickup Location:* Hotel Majapahit Surabaya 08:00 - *Guests (Pax):* 2 - *Status:* Confirmed *Payment Summary* - *Payment Received:* IDR 3.250.000 - *Payment Type:* Balance Payment - *Payment Status:* Partially Paid *Trip Dashboard* 📊 View your itinerary, pickup details, accommodation, and trip updates here: 👉 https://jvto.me/b/Ab3dE5fG7h *Notes* - Any confirmed updates will appear in the Trip Dashboard. - If a remaining balance applies, we will share the payment link and deadline in a separate message. - Please review the Trip Dashboard and tell us if any details need correction. *Need help?* Reply to this chat or contact: - WhatsApp: +62 822-4478-8833 - Email: hello@javavolcano-touroperator.com *Security:* JVTO will never ask for your OTP/PIN. Please use only official links shared in this chat. — JVTO Team | K9: ✅ *[PAYMENT RECEIVED] Your booking is confirmed* 🎉 Hi _John Doe_, thank you for your payment. 🧾 *Booking ID:* `JVTO-2026-0001` 🗺️ *Tour Package:* Bromo Ijen Tour 3 Days 2 Nights 📅 *Travel Dates:* 12 October 2026 – 14 October 2026 📍 *Pickup:* Hotel Majapahit Surabaya 08:00 👥 *Guests:* 2 pax ✅ *Status:* Confirmed 💰 *Payment Received:* `IDR 3.250.000` 💳 *Payment Type:* Balance Payment 📊 *Payment Status:* Partially Paid 📌 *Please note* - Confirmed updates appear in your Trip Dashboard. - If a remaining balance applies, we will send the payment link and deadline separately. 💬 *Need help?* Reply to this chat, WhatsApp +62 822-4478-8833 or email hello@javavolcano-touroperator.com 👉 *Review your itinerary, pickup and accommodation in the Trip Dashboard — tell us if anything needs correcting:* https://jvto.me/b/Ab3dE5fG7h _🔒 JVTO will never ask for your OTP/PIN. Please use only official links shared in this chat. — JVTO Team_ | L9: Detail booking 6 baris dipecah jadi 2 blok ≤3 baris; ID booking & nominal monospace; catatan ke-3 ('periksa dashboard & kabari koreksi') dijadikan CTA tebal bersama tautan dashboard di bawah; blok kontak dipadatkan jadi 1 baris; peringatan keamanan jadi catatan kaki miring. Tautan portal booking: jvto.me/b/{booking_short} — sudah aktif di produksi sejak 22 Sep 2026 (template lama ikut diganti). | M9: =IF('Cek Kepatuhan'!X9=0,"Lulus: "&'Cek Kepatuhan'!V9&" OK, "&'Cek Kepatuhan'!W9&" N/A","GAGAL "&'Cek Kepatuhan'!X9&" aturan")
A10: 9 | B10: payment_received_first | C10: Pembayaran pertama diterima — booking terkonfirmasi | D10: Pelanggan | E10: Dikirim ke pelanggan (gambar + caption) saat webhook Xendit menerima pembayaran pertama (DP/penuh) dan booking menjadi booked. Teks yang sama juga diteruskan ke grup internal JVTO. | F10: Ya | G10: customer_name* booking_code* package_name* travel_date_start* travel_date_end* pickup* total_pax* payment_amount* payment_type* payment_status* booking_slug* booking_short* | H10: *[JVTO] Booking Confirmed — Payment Received* ✅🎉 Hi _{customer_name}_, thank you for your payment. Your booking is now *confirmed*. *Booking Details* - *Booking ID:* {booking_code} - *Tour Package:* {package_name} - *Travel Dates:* {travel_date_start} - {travel_date_end} -- *Pickup Location:* {pickup} - *Guests (Pax):* {total_pax} - *Status:* Confirmed *Payment Summary* - *Payment Received:* IDR {payment_amount} - *Payment Type:* {payment_type} - *Payment Status:* {payment_status} *Trip Dashboard* 📊 View your itinerary, pickup details, accommodation, and trip updates here: 👉 https://jvto.me/b/{booking_short} *Notes* - Any confirmed updates will appear in the Trip Dashboard. - If a remaining balance applies, we will share the payment link and deadline in a separate message. - Please review the Trip Dashboard and tell us if any details need correction. *Need help?* Reply to this chat or contact: - WhatsApp: +62 822-4478-8833 - Email: hello@javavolcano-touroperator.com *Security:* JVTO will never ask for your OTP/PIN. Please use only official links shared in this chat. — JVTO Team | I10: ✅ *[PAYMENT RECEIVED] Your booking is confirmed* 🎉 Hi _{customer_name}_, thank you for your payment. 🧾 *Booking ID:* `{booking_code}` 🗺️ *Tour Package:* {package_name} 📅 *Travel Dates:* {travel_date_start} – {travel_date_end} 📍 *Pickup:* {pickup} 👥 *Guests:* {total_pax} pax ✅ *Status:* Confirmed 💰 *Payment Received:* `IDR {payment_amount}` 💳 *Payment Type:* {payment_type} 📊 *Payment Status:* {payment_status} 📌 *Please note* - Confirmed updates appear in your Trip Dashboard. - If a remaining balance applies, we will send the payment link and deadline separately. 💬 *Need help?* Reply to this chat, WhatsApp +62 822-4478-8833 or email hello@javavolcano-touroperator.com 👉 *Review your itinerary, pickup and accommodation in the Trip Dashboard — tell us if anything needs correcting:* https://jvto.me/b/{booking_short} _🔒 JVTO will never ask for your OTP/PIN. Please use only official links shared in this chat. — JVTO Team_ | J10: *[JVTO] Booking Confirmed — Payment Received* ✅🎉 Hi _John Doe_, thank you for your payment. Your booking is now *confirmed*. *Booking Details* - *Booking ID:* JVTO-2026-0001 - *Tour Package:* Bromo Ijen Tour 3 Days 2 Nights - *Travel Dates:* 12 October 2026 - 14 October 2026 -- *Pickup Location:* Hotel Majapahit Surabaya 08:00 - *Guests (Pax):* 2 - *Status:* Confirmed *Payment Summary* - *Payment Received:* IDR 1.500.000 - *Payment Type:* Deposit - *Payment Status:* Partially Paid *Trip Dashboard* 📊 View your itinerary, pickup details, accommodation, and trip updates here: 👉 https://jvto.me/b/Ab3dE5fG7h *Notes* - Any confirmed updates will appear in the Trip Dashboard. - If a remaining balance applies, we will share the payment link and deadline in a separate message. - Please review the Trip Dashboard and tell us if any details need correction. *Need help?* Reply to this chat or contact: - WhatsApp: +62 822-4478-8833 - Email: hello@javavolcano-touroperator.com *Security:* JVTO will never ask for your OTP/PIN. Please use only official links shared in this chat. — JVTO Team | K10: ✅ *[PAYMENT RECEIVED] Your booking is confirmed* 🎉 Hi _John Doe_, thank you for your payment. 🧾 *Booking ID:* `JVTO-2026-0001` 🗺️ *Tour Package:* Bromo Ijen Tour 3 Days 2 Nights 📅 *Travel Dates:* 12 October 2026 – 14 October 2026 📍 *Pickup:* Hotel Majapahit Surabaya 08:00 👥 *Guests:* 2 pax ✅ *Status:* Confirmed 💰 *Payment Received:* `IDR 1.500.000` 💳 *Payment Type:* Deposit 📊 *Payment Status:* Partially Paid 📌 *Please note* - Confirmed updates appear in your Trip Dashboard. - If a remaining balance applies, we will send the payment link and deadline separately. 💬 *Need help?* Reply to this chat, WhatsApp +62 822-4478-8833 or email hello@javavolcano-touroperator.com 👉 *Review your itinerary, pickup and accommodation in the Trip Dashboard — tell us if anything needs correcting:* https://jvto.me/b/Ab3dE5fG7h _🔒 JVTO will never ask for your OTP/PIN. Please use only official links shared in this chat. — JVTO Team_ | L10: Sama dengan payment_received_balance; sekalian membuang typo '-- *Pickup Location:*' dari versi lama. Ingat: teks ini juga dikirim ke grup internal JVTO. Tautan portal booking: jvto.me/b/{booking_short} — sudah aktif di produksi sejak 22 Sep 2026 (template lama ikut diganti). | M10: =IF('Cek Kepatuhan'!X10=0,"Lulus: "&'Cek Kepatuhan'!V10&" OK, "&'Cek Kepatuhan'!W10&" N/A","GAGAL "&'Cek Kepatuhan'!X10&" aturan")
A11: 10 | B11: payment_reminder_balance | C11: Pengingat pelunasan H-7 | D11: Pelanggan | E11: Dikirim ke pelanggan pukul 15:00 tujuh hari sebelum trip bila masih ada sisa tagihan (non-Klook), berisi tautan invoice Xendit baru dan tenggat pelunasan. | F11: — | G11: customer_name* booking_code* package_name* travel_date_start* travel_date_end* pickup* total_pax* total_amount* deposit_paid* outstanding_balance* card_due_date* transfer_due_date* card_payment_link* booking_slug* booking_short* | H11: *[JVTO] Payment Reminder — Balance Payment Required* ⏰ Hi _{customer_name}_, this is a reminder that your booking is confirmed and the *remaining balance* is still unpaid. *Booking Details* - *Booking ID:* {booking_code} - *Tour Package:* {package_name} - *Travel Dates:* {travel_date_start} - {travel_date_end} - *Trip Day 1:* {travel_date_start} - *Pickup Location:* {pickup} - *Guests (Pax):* {total_pax} - *Status:* Confirmed (Deposit Paid) *Payment Summary* - *Total Amount:* IDR {total_amount} - *Deposit Paid:* IDR {deposit_paid} - *Outstanding Balance:* IDR {outstanding_balance} *Balance Payment Deadline* - *Card:* {card_due_date} *(no later than 5 days before Day 1)* - *Bank Transfer / Wise:* {transfer_due_date} *(no later than 3 days before Day 1)* *Pay the Balance* - *Card Payment:* 👉 {card_payment_link} - *Bank Transfer / Wise instructions:* 👉 https://jvto.me/b/{booking_short} *Notes* - Full payment is required before the trip so we can finalize all operational arrangements. - Please pay before the deadline to avoid disruptions. *Need help?* Reply to this chat or contact: - WhatsApp: +62 822-4478-8833 - Email: hello@javavolcano-touroperator.com *Security:* JVTO will never ask for your OTP/PIN. Please use only official links shared by JVTO. — JVTO Team | I11: ⏰ *[PAYMENT REMINDER] Balance due before your trip* Hi _{customer_name}_, your booking is confirmed (deposit paid). The *remaining balance* is still unpaid. 🧾 *Booking ID:* `{booking_code}` 🗺️ *Tour Package:* {package_name} 📅 *Travel Dates:* {travel_date_start} – {travel_date_end} (Day 1: {travel_date_start}) 📍 *Pickup:* {pickup} 👥 *Guests:* {total_pax} pax 💰 *Total Amount:* IDR {total_amount} ✅ *Deposit Paid:* IDR {deposit_paid} 🔴 *Outstanding Balance:* `IDR {outstanding_balance}` 🗓️ *Payment deadline* - *Card:* {card_due_date} _(no later than 5 days before Day 1)_ - *Bank Transfer / Wise:* {transfer_due_date} _(no later than 3 days before Day 1)_ _Full payment before the trip lets us finalize all operational arrangements — please pay before the deadline to avoid disruptions._ 💬 *Need help?* Reply to this chat, WhatsApp +62 822-4478-8833 or email hello@javavolcano-touroperator.com 👉 *Pay by card now:* {card_payment_link} 👉 *Bank Transfer / Wise instructions:* https://jvto.me/b/{booking_short} _🔒 JVTO will never ask for your OTP/PIN. Please use only official links shared by JVTO. — JVTO Team_ | J11: *[JVTO] Payment Reminder — Balance Payment Required* ⏰ Hi _John Doe_, this is a reminder that your booking is confirmed and the *remaining balance* is still unpaid. *Booking Details* - *Booking ID:* JVTO-2026-0001 - *Tour Package:* Bromo Ijen Tour 3 Days 2 Nights - *Travel Dates:* 12 Oct 2026 - 14 Oct 2026 - *Trip Day 1:* 12 Oct 2026 - *Pickup Location:* Hotel Majapahit Surabaya 08:00 - *Guests (Pax):* 2 - *Status:* Confirmed (Deposit Paid) *Payment Summary* - *Total Amount:* IDR 4,750,000 - *Deposit Paid:* IDR 1,500,000 - *Outstanding Balance:* IDR 3,250,000 *Balance Payment Deadline* - *Card:* 07 Oct 2026 *(no later than 5 days before Day 1)* - *Bank Transfer / Wise:* 09 Oct 2026 *(no later than 3 days before Day 1)* *Pay the Balance* - *Card Payment:* 👉 https://checkout.xendit.co/web/example-invoice-0003 - *Bank Transfer / Wise instructions:* 👉 https://jvto.me/b/Ab3dE5fG7h *Notes* - Full payment is required before the trip so we can finalize all operational arrangements. - Please pay before the deadline to avoid disruptions. *Need help?* Reply to this chat or contact: - WhatsApp: +62 822-4478-8833 - Email: hello@javavolcano-touroperator.com *Security:* JVTO will never ask for your OTP/PIN. Please use only official links shared by JVTO. — JVTO Team | K11: ⏰ *[PAYMENT REMINDER] Balance due before your trip* Hi _John Doe_, your booking is confirmed (deposit paid). The *remaining balance* is still unpaid. 🧾 *Booking ID:* `JVTO-2026-0001` 🗺️ *Tour Package:* Bromo Ijen Tour 3 Days 2 Nights 📅 *Travel Dates:* 12 Oct 2026 – 14 Oct 2026 (Day 1: 12 Oct 2026) 📍 *Pickup:* Hotel Majapahit Surabaya 08:00 👥 *Guests:* 2 pax 💰 *Total Amount:* IDR 4,750,000 ✅ *Deposit Paid:* IDR 1,500,000 🔴 *Outstanding Balance:* `IDR 3,250,000` 🗓️ *Payment deadline* - *Card:* 07 Oct 2026 _(no later than 5 days before Day 1)_ - *Bank Transfer / Wise:* 09 Oct 2026 _(no later than 3 days before Day 1)_ _Full payment before the trip lets us finalize all operational arrangements — please pay before the deadline to avoid disruptions._ 💬 *Need help?* Reply to this chat, WhatsApp +62 822-4478-8833 or email hello@javavolcano-touroperator.com 👉 *Pay by card now:* https://checkout.xendit.co/web/example-invoice-0003 👉 *Bank Transfer / Wise instructions:* https://jvto.me/b/Ab3dE5fG7h _🔒 JVTO will never ask for your OTP/PIN. Please use only official links shared by JVTO. — JVTO Team_ | L11: Hook berlabel [PAYMENT REMINDER]; detail 6 baris dipecah jadi 2 blok; hanya sisa tagihan yang di-monospace (angka yang harus dibayar menonjol dari total & deposit); keterangan tenggat dimiringkan; dua catatan digabung jadi 1 kalimat miring; dua tautan bayar jadi CTA tebal di bawah. Strikethrough TIDAK dipakai: total vs deposit bukan harga coret/diskon, mencoretnya akan menyesatkan. Tautan portal booking: jvto.me/b/{booking_short} — sudah aktif di produksi sejak 22 Sep 2026 (template lama ikut diganti). | M11: =IF('Cek Kepatuhan'!X11=0,"Lulus: "&'Cek Kepatuhan'!V11&" OK, "&'Cek Kepatuhan'!W11&" N/A","GAGAL "&'Cek Kepatuhan'!X11&" aturan")
A12: 11 | B12: trip_concluded | C12: Trip selesai — foto & ulasan | D12: Pelanggan | E12: Dikirim ke pelanggan pada jadwal wa_schedule_trip_media setelah trip: ucapan terima kasih, tautan foto di dashboard, dan ajakan memberi ulasan. | F12: — | G12: customer_name* booking_slug* booking_short* | H12: Hello {customer_name} 🌟 *Your Journey with JVTO Concludes!* 🏜 Thank you so much for choosing *Java Volcano Tour Operator* for your adventure! We truly hope you had a fun and unforgettable trip in Indonesia. 📸 Your Trip Memories: All the fantastic pictures from your trip are ready for you to view and download! Access them directly on your personalized trip dashboard: 🌐 https://jvto.me/b/{booking_short} ✍ Share Your Experience: Your feedback is invaluable to us and incredibly helpful to future travelers. Please take a moment to leave a review on Google or Trustpilot (link also available on portal). We hope to welcome you on another adventure soon! Many thanks, The JVTO Team | I12: 🌟 *[TRIP COMPLETE] Thank you for traveling with JVTO!* Hello _{customer_name}_, we truly hope you had a fun and unforgettable trip in Indonesia. 📸 *Your trip photos are ready* to view and download in your personal trip dashboard. ✍️ *Share your experience:* a review on Google or Trustpilot helps future travelers (the links are in your dashboard). 👉 *Open your photos and leave a review here:* https://jvto.me/b/{booking_short} _We hope to welcome you on another adventure soon! Many thanks — The JVTO Team_ | J12: Hello John Doe 🌟 *Your Journey with JVTO Concludes!* 🏜 Thank you so much for choosing *Java Volcano Tour Operator* for your adventure! We truly hope you had a fun and unforgettable trip in Indonesia. 📸 Your Trip Memories: All the fantastic pictures from your trip are ready for you to view and download! Access them directly on your personalized trip dashboard: 🌐 https://jvto.me/b/Ab3dE5fG7h ✍ Share Your Experience: Your feedback is invaluable to us and incredibly helpful to future travelers. Please take a moment to leave a review on Google or Trustpilot (link also available on portal). We hope to welcome you on another adventure soon! Many thanks, The JVTO Team | K12: 🌟 *[TRIP COMPLETE] Thank you for traveling with JVTO!* Hello _John Doe_, we truly hope you had a fun and unforgettable trip in Indonesia. 📸 *Your trip photos are ready* to view and download in your personal trip dashboard. ✍️ *Share your experience:* a review on Google or Trustpilot helps future travelers (the links are in your dashboard). 👉 *Open your photos and leave a review here:* https://jvto.me/b/Ab3dE5fG7h _We hope to welcome you on another adventure soon! Many thanks — The JVTO Team_ | L12: Sapaan + judul jadi satu hook berlabel; dua ajakan (lihat foto, beri ulasan) disatukan jadi satu CTA tebal di bawah dengan satu tautan; penutup miring. Tautan portal booking: jvto.me/b/{booking_short} — sudah aktif di produksi sejak 22 Sep 2026 (template lama ikut diganti). | M12: =IF('Cek Kepatuhan'!X12=0,"Lulus: "&'Cek Kepatuhan'!V12&" OK, "&'Cek Kepatuhan'!W12&" N/A","GAGAL "&'Cek Kepatuhan'!X12&" aturan")
A13: 12 | B13: trip_daily_itinerary | C13: Itinerary harian ke pelanggan | D13: Pelanggan | E13: Dikirim ke pelanggan setiap malam selama trip (jadwal dari new-backoffice, tabel WaItinerary) lewat /backoffice/send-wa/test di javavolcano-touroperator. | F13: — | G13: customer_name* itinerary* | H13: *Hello {customer_name}.* {itinerary} | I13: 🗓️ *[YOUR ITINERARY] Hello {customer_name}!* {itinerary} 👉 *Reply to this chat* if you have any questions about this plan. _— JVTO Team_ | J13: *Hello John Doe.* *Day 1 - Ijen Crater* Midnight hike to the blue fire. | K13: 🗓️ *[YOUR ITINERARY] Hello John Doe!* *Day 1 - Ijen Crater* Midnight hike to the blue fire. 👉 *Reply to this chat* if you have any questions about this plan. _— JVTO Team_ | L13: Hook berlabel + emoji; itinerary dipisah dengan baris kosong; ditambah CTA tebal. Isi itinerary adalah teks bebas dari admin (WaItinerary), jadi panjang bloknya tidak bisa dijamin oleh template — admin perlu menulisnya pendek-pendek sendiri. | M13: =IF('Cek Kepatuhan'!X13=0,"Lulus: "&'Cek Kepatuhan'!V13&" OK, "&'Cek Kepatuhan'!W13&" N/A","GAGAL "&'Cek Kepatuhan'!X13&" aturan")
... A24: 23 | B24: vendor_tshirt_size_update | C24: Update ukuran kaos ke vendor | D24: Internal / crew / hotel / vendor | E24: Dikirim ke vendor kaos saat rincian ukuran kaos sebuah booking berubah di new-backoffice. | F24: — | G24: customer_name* trip_date* channel* sizes* | H24: *🎽 Update Size T-Shirt* Nama Customer: {customer_name} Tanggal Trip: {trip_date} Channel: {channel} Size: {sizes} | I24: 🎽 *[UPDATE SIZE KAOS] {customer_name}* 📅 Tanggal Trip: {trip_date} 🏷 Channel: {channel} 📏 Size: `{sizes}` 👉 *Mohon sesuaikan* produksi kaos dengan ukuran terbaru di atas. | J24: *🎽 Update Size T-Shirt* Nama Customer: John Doe Tanggal Trip: 12 Oct 2026 Channel: JVTO Size: S x 1; M x 2; XL x 1 | K24: 🎽 *[UPDATE SIZE KAOS] John Doe* 📅 Tanggal Trip: 12 Oct 2026 🏷 Channel: JVTO 📏 Size: `S x 1; M x 2; XL x 1` 👉 *Mohon sesuaikan* produksi kaos dengan ukuran terbaru di atas. | L24: Nama pelanggan naik ke hook; ukuran (inti pesan) diisolasi dengan monospace di blok sendiri; ditambah CTA tebal. Kalimat CTA adalah teks baru. | M24: =IF('Cek Kepatuhan'!X24=0,"Lulus: "&'Cek Kepatuhan'!V24&" OK, "&'Cek Kepatuhan'!W24&" N/A","GAGAL "&'Cek Kepatuhan'!X24&" aturan")

Sheet Panduan per Poin
A1: ID | B1: Bagian panduan | C1: Isi poin (ringkasan setia) | D1: Cara diterapkan di draft | E1: Aturan pemeriksa mesin
A2: G1 | B2: 1. Pemrosesan Informasi Kognitif — Cognitive Load | C2: Working memory terbatas; pesan satu paragraf panjang tanpa format membuat beban kognitif tinggi, otak harus mencari inti pesan, dan pesan cenderung diabaikan/ditutup. | D2: Tidak ada paragraf panjang: kalimat dipendekkan, satu gagasan per baris. | E2: G1: tidak ada baris teks >180 karakter (±4 baris di layar ponsel).
A3: G2 | B3: 1. Pemrosesan Informasi Kognitif — Metode Chunking | C3: Pecah informasi besar menjadi blok logis; di WhatsApp: paragraf pendek maksimal 2–3 baris per blok, dipisah baris kosong. 3 paragraf pendek lebih mudah dicerna daripada 1 paragraf panjang walau jumlah katanya sama. | D3: Daftar detail yang dulu 5–6 baris dipecah jadi blok 2–3 baris yang berkelompok logis (identitas booking | logistik | pembayaran). | E3: G2: setiap blok ≤3 baris. Isi variabel bebas dari admin (itinerary, isi payment arrangement, daftar crew) dihitung 1 baris — panjangnya di luar kendali template.
A4: G3 | B4: 2. Perilaku Membaca Digital — Scanning | C4: Riset eye-tracking (Nielsen Norman Group): pembaca layar memindai, tidak membaca kata demi kata. | D4: Diwujudkan lewat G4–G7 (hook, kata kunci di kiri, jangkar emoji, CTA di bawah). | E4: — (tercakup oleh G4, G5, G6, G7)
A5: G4 | B5: 2. Pola F-Shape | C5: Pembaca membaca baris paling atas secara horizontal dulu → letakkan Headline/Hook tebal (*...*) di baris pertama. | D5: Baris 1 setiap template adalah hook tebal. | E5: G4: baris 1 memuat teks tebal.
A6: G5 | B6: 2. Pola F-Shape | C6: Setelah baris atas, mata turun memindai sisi kiri secara vertikal → kata kunci penting di awal kalimat sebelah kiri. | D6: Setiap baris data diawali label (Booking ID, Pickup, Amount Due, dst.) di sisi kiri, sesudah emoji. | E6: G5: setiap label "X:" berada di awal baris; sebelum label hanya boleh emoji/spasi/tanda format.
A7: G6 | B7: 2. Pola Z-Shape | C7: Untuk pesan pendek/banyak elemen visual: gunakan emoji sebagai visual anchor di sisi kiri untuk menarik mata. | D7: Setiap blok isi diawali emoji yang mewakili isinya (🧾 ID, 📍 lokasi, 💰 uang, 💬 bantuan, 👉 aksi). | E7: G6: setiap blok (selain kalimat sapaan, isi bebas, dan catatan kaki) diawali emoji.
A8: G7 | B8: 2. Pola Z-Shape | C8: Mata berakhir di kanan bawah → kunci perhatian terakhir dengan tombol aksi atau instruksi pembayaran (CTA). | D8: Tautan/aksi utama dipindah ke blok terakhir sebelum catatan kaki, diberi 👉. | E8: G7: blok terakhir (di luar catatan kaki miring) berisi baris CTA 👉.
A9: G8 | B9: 3. Atensi Selektif & Gestalt (Similarity & Contrast) | C9: Manusia memperhatikan stimulus yang berbeda dari sekitarnya; objek yang tampak berbeda dianggap lebih penting. Kata tebal di tengah teks polos menciptakan kontras — konsekuensinya, kontras hilang bila hampir semua teks tebal. | D9: Tebal dipakai hemat: hook, label data (di pesan panjang), dan frasa aksi CTA. Di pesan internal yang pendek, label tidak ditebalkan supaya hook & CTA tetap menonjol. | E9: G8: porsi teks tebal ≤40% dari seluruh teks (dihitung dengan nilai contoh, tanpa format dari isi variabel). Batas 40% adalah asumsi penyusun, bukan angka dari panduan.
A10: G9 | B10: 3. Metode Visual Anchors | C10: Bold, Italic, dan Monospace bertindak sebagai jangkar yang menghentikan laju scrolling; otak melompati teks biasa dan membaca kata tebal lebih dulu. | D10: Tiap format punya satu peran tetap: Bold = hook, label, aksi; Monospace = data yang harus dibaca persis; Italic = catatan kaki. | E10: — (tercakup oleh G4, G8, G12, G13, G16)
A11: G10 | B11: 4. Inverted Pyramid — Puncak | C11: Paling atas: core value / urgensi utama — mengapa pelanggan harus membaca chat ini (contoh: [KONFIRMASI PENGIRIMAN], PROMO TERBATAS). | D11: Hook memuat label urgensi dalam kurung siku: [PAYMENT REQUIRED], [PAYMENT RECEIVED], [TOMORROW], [RESERVASI KAMAR], dst. | E11: G10: baris 1 memuat label [HURUF KAPITAL].
A12: G11 | B12: 4. Inverted Pyramid — Badan (kontras harga) | C12: Badan berisi detail instruksi, angka, data teknis; gunakan ~coret~ untuk kontras harga. | D12: TIDAK diterapkan, dengan sengaja: tidak ada satu pun template yang membawa harga lama vs harga baru (diskon). Mencoret total/deposit akan terbaca sebagai diskon dan menyesatkan pelanggan. | E12: G11: tanda ~ tidak boleh muncul di draft mana pun (N/A).
... A18: G17 | B18: Penutup panduan | C18: Setiap huruf tebal, miring, atau spasi harus punya alasan; jangan menebak-nebak. | D18: Alasan setiap perubahan ditulis per template di kolom "Perubahan utama & alasan". | E18: — (diperiksa manusia; lihat kolom Perubahan utama)
A20: Aturan integritas (bukan dari panduan — menjamin draft tidak merusak isi)
A21: I1 | B21: Tidak ada informasi yang hilang | C21: Semua variabel yang dipakai template lama tetap dipakai draft.
A22: I2 | B22: Draft valid untuk wa-inbox | C22: Lolos validateTemplateBody (tidak memakai variabel yang tidak dikirim program pemanggil) — draft bisa langsung disimpan di Template Sistem.
A23: I3 | B23: Tidak ada fakta baru | C23: Setiap URL, nomor telepon, dan email di draft sudah ada di salah satu template lama.
A24: I4 | B24: Bisa dirender | C24: Terender dengan renderer produksi wa-inbox memakai nilai contoh.
A25: I5 | B25: Baris opsional hilang bersih | C25: Bila variabel opsional kosong (mis. Drop, Special Requirements, Makan), barisnya hilang tanpa sisa label.

Sheet Cek Kepatuhan
A1: No | B1: Key | C1: G1 | D1: G2 | E1: G4 | F1: G5 | G1: G6 | H1: G7 | I1: G8 | J1: G10 | K1: G11 | L1: G12 | M1: G13 | N1: G14 | O1: G15 | P1: G16 | Q1: I1 | R1: I2 | S1: I3 | T1: I4 | U1: I5 | V1: OK | W1: N/A | X1: GAGAL
A2: 1 | B2: booking_confirmed_backoffice_jvto | C2: OK | D2: OK | E2: OK | F2: OK | G2: OK | H2: OK | I2: OK | J2: OK | K2: N/A | L2: N/A | M2: OK | N2: OK | O2: OK | P2: OK | Q2: OK | R2: OK | S2: OK | T2: OK | U2: N/A | V2: =COUNTIF(C2:U2,"OK") | W2: =COUNTIF(C2:U2,"N/A") | X2: =COUNTIF(C2:U2,"GAGAL")
A3: 2 | B3: booking_confirmed_backoffice_klook | C3: OK | D3: OK | E3: OK | F3: OK | G3: OK | H3: OK | I3: OK | J3: OK | K3: N/A | L3: N/A | M3: OK | N3: OK | O3: OK | P3: OK | Q3: OK | R3: OK | S3: OK | T3: OK | U3: N/A | V3: =COUNTIF(C3:U3,"OK") | W3: =COUNTIF(C3:U3,"N/A") | X3: =COUNTIF(C3:U3,"GAGAL")
A4: 3 | B4: booking_confirmed_klook_email | C4: OK | D4: OK | E4: OK | F4: OK | G4: OK | H4: OK | I4: OK | J4: OK | K4: N/A | L4: N/A | M4: OK | N4: OK | O4: OK | P4: OK | Q4: OK | R4: OK | S4: OK | T4: OK | U4: N/A | V4: =COUNTIF(C4:U4,"OK") | W4: =COUNTIF(C4:U4,"N/A") | X4: =COUNTIF(C4:U4,"GAGAL")
A5: 4 | B5: booking_pending_payment | C5: OK | D5: OK | E5: OK | F5: OK | G5: OK | H5: OK | I5: OK | J5: OK | K5: N/A | L5: OK | M5: OK | N5: OK | O5: OK | P5: OK | Q5: OK | R5: OK | S5: OK | T5: OK | U5: N/A | V5: =COUNTIF(C5:U5,"OK") | W5: =COUNTIF(C5:U5,"N/A") | X5: =COUNTIF(C5:U5,"GAGAL")
A6: 5 | B6: payment_method_confirmed_card | C6: OK | D6: OK | E6: OK | F6: OK | G6: OK | H6: OK | I6: OK | J6: OK | K6: N/A | L6: OK | M6: OK | N6: OK | O6: OK | P6: OK | Q6: OK | R6: OK | S6: OK | T6: OK | U6: N/A | V6: =COUNTIF(C6:U6,"OK") | W6: =COUNTIF(C6:U6,"N/A") | X6: =COUNTIF(C6:U6,"GAGAL")
A7: 6 | B7: payment_method_confirmed_cash | C7: OK | D7: OK | E7: OK | F7: OK | G7: OK | H7: OK | I7: OK | J7: OK | K7: N/A | L7: OK | M7: OK | N7: OK | O7: OK | P7: OK | Q7: OK | R7: OK | S7: OK | T7: OK | U7: N/A | V7: =COUNTIF(C7:U7,"OK") | W7: =COUNTIF(C7:U7,"N/A") | X7: =COUNTIF(C7:U7,"GAGAL")
A8: 7 | B8: payment_method_confirmed_wise | C8: OK | D8: OK | E8: OK | F8: OK | G8: OK | H8: OK | I8: OK | J8: OK | K8: N/A | L8: OK | M8: OK | N8: OK | O8: OK | P8: OK | Q8: OK | R8: OK | S8: OK | T8: OK | U8: N/A | V8: =COUNTIF(C8:U8,"OK") | W8: =COUNTIF(C8:U8,"N/A") | X8: =COUNTIF(C8:U8,"GAGAL")
A9: 8 | B9: payment_received_balance | C9: OK | D9: OK | E9: OK | F9: OK | G9: OK | H9: OK | I9: OK | J9: OK | K9: N/A | L9: OK | M9: OK | N9: OK | O9: OK | P9: OK | Q9: OK | R9: OK | S9: OK | T9: OK | U9: N/A | V9: =COUNTIF(C9:U9,"OK") | W9: =COUNTIF(C9:U9,"N/A") | X9: =COUNTIF(C9:U9,"GAGAL")
A10: 9 | B10: payment_received_first | C10: OK | D10: OK | E10: OK | F10: OK | G10: OK | H10: OK | I10: OK | J10: OK | K10: N/A | L10: OK | M10: OK | N10: OK | O10: OK | P10: OK | Q10: OK | R10: OK | S10: OK | T10: OK | U10: N/A | V10: =COUNTIF(C10:U10,"OK") | W10: =COUNTIF(C10:U10,"N/A") | X10: =COUNTIF(C10:U10,"GAGAL")
A11: 10 | B11: payment_reminder_balance | C11: OK | D11: OK | E11: OK | F11: OK | G11: OK | H11: OK | I11: OK | J11: OK | K11: N/A | L11: OK | M11: OK | N11: OK | O11: OK | P11: OK | Q11: OK | R11: OK | S11: OK | T11: OK | U11: N/A | V11: =COUNTIF(C11:U11,"OK") | W11: =COUNTIF(C11:U11,"N/A") | X11: =COUNTIF(C11:U11,"GAGAL")
A12: 11 | B12: trip_concluded | C12: OK | D12: OK | E12: OK | F12: OK | G12: OK | H12: OK | I12: OK | J12: OK | K12: N/A | L12: N/A | M12: OK | N12: OK | O12: OK | P12: OK | Q12: OK | R12: OK | S12: OK | T12: OK | U12: N/A | V12: =COUNTIF(C12:U12,"OK") | W12: =COUNTIF(C12:U12,"N/A") | X12: =COUNTIF(C12:U12,"GAGAL")
A13: 12 | B13: trip_daily_itinerary | C13: OK | D13: OK | E13: OK | F13: OK | G13: OK | H13: OK | I13: OK | J13: OK | K13: N/A | L13: N/A | M13: OK | N13: OK | O13: OK | P13: OK | Q13: OK | R13: OK | S13: OK | T13: OK | U13: N/A | V13: =COUNTIF(C13:U13,"OK") | W13: =COUNTIF(C13:U13,"N/A") | X13: =COUNTIF(C13:U13,"GAGAL")
... A24: 23 | B24: vendor_tshirt_size_update | C24: OK | D24: OK | E24: OK | F24: OK | G24: OK | H24: OK | I24: OK | J24: OK | K24: N/A | L24: OK | M24: N/A | N24: OK | O24: OK | P24: OK | Q24: OK | R24: OK | S24: OK | T24: OK | U24: N/A | V24: =COUNTIF(C24:U24,"OK") | W24: =COUNTIF(C24:U24,"N/A") | X24: =COUNTIF(C24:U24,"GAGAL")
B25: Jumlah template GAGAL per aturan | C25: =COUNTIF(C2:C24,"GAGAL") | D25: =COUNTIF(D2:D24,"GAGAL") | E25: =COUNTIF(E2:E24,"GAGAL") | F25: =COUNTIF(F2:F24,"GAGAL") | G25: =COUNTIF(G2:G24,"GAGAL") | H25: =COUNTIF(H2:H24,"GAGAL") | I25: =COUNTIF(I2:I24,"GAGAL") | J25: =COUNTIF(J2:J24,"GAGAL") | ... U25: =COUNTIF(U2:U24,"GAGAL") | V25: =SUM(V2:V24) | W25: =SUM(W2:W24) | X25: =SUM(X2:X24)
B27: Arti ID aturan ada di sheet "Panduan per Poin". Catatan per sel ada di sheet "Detail Cek".

Sheet Detail Cek
A1: Key | B1: Aturan | C1: Status | D1: Catatan pemeriksa
A2: booking_confirmed_backoffice_jvto | B2: G1 | C2: OK | D2: tidak ada paragraf panjang
A3: booking_confirmed_backoffice_jvto | B3: G2 | C3: OK | D3: blok terpanjang 2 baris
A4: booking_confirmed_backoffice_jvto | B4: G4 | C4: OK | D4: ✅ *[BOOKING CONFIRMED] Your JVTO tour is secured*
A5: booking_confirmed_backoffice_jvto | B5: G5 | C5: OK | D5: kata kunci/label di awal baris kiri
A6: booking_confirmed_backoffice_jvto | B6: G6 | C6: OK | D6: setiap blok diawali emoji
A7: booking_confirmed_backoffice_jvto | B7: G7 | C7: OK | D7: CTA 👉 di blok terakhir
A8: booking_confirmed_backoffice_jvto | B8: G8 | C8: OK | D8: porsi teks tebal 23% (maks 40%)
A9: booking_confirmed_backoffice_jvto | B9: G10 | C9: OK | D9: label [URGENSI] di baris 1
A10: booking_confirmed_backoffice_jvto | B10: G11 | C10: N/A | D10: tidak ada harga coret — tidak dipakai (N/A)
A11: booking_confirmed_backoffice_jvto | B11: G12 | C11: N/A | D11: tidak ada ID/nominal (N/A)
A12: booking_confirmed_backoffice_jvto | B12: G13 | C12: OK | D12: 1 baris catatan kaki miring
... A438: vendor_tshirt_size_update | B438: I5 | C438: N/A | D438: tidak punya variabel opsional (N/A)
